c4m/cell_canvas.ipynb
c4m/flexcell/__init__.py
c4m/flexcell/_waiters.py
c4m/flexcell/activecolumnscell.py
c4m/flexcell/canvas.py
c4m/flexcell/cell.py
c4m/flexcell/factory.py
c4m_flexcell-0.4.6.dist-info/METADATA
c4m_flexcell-0.4.6.dist-info/WHEEL
c4m_flexcell-0.4.6.dist-info/entry_points.txt
c4m_flexcell-0.4.6.dist-info/licenses/LICENSE.md
c4m_flexcell-0.4.6.dist-info/RECORD
